chemfit/__init__.py
chemfit/abstract_objective_function.py
chemfit/ase_objective_function.py
chemfit/combined_objective_function.py
chemfit/data_utils.py
chemfit/debug_utils.py
chemfit/fitter.py
chemfit/kabsch.py
chemfit/mpi_wrapper_cob.py
chemfit/plot_utils.py
chemfit/scme_factories.py
chemfit/scme_setup.py
chemfit/utils.py
chemfit-3.0.0.dist-info/licenses/LICENSE
chemfit-3.0.0.dist-info/METADATA
chemfit-3.0.0.dist-info/WHEEL
chemfit-3.0.0.dist-info/top_level.txt
chemfit-3.0.0.dist-info/RECORD
